bison/__init__.py
bison/__version__.py
bison/bison.py
bison/errors.py
bison/scheme.py
bison/utils.py
tests/__init__.py
tests/conftest.py
tests/test_bison.py
tests/test_scheme.py
tests/test_utils.py
bison-0.1.2.dist-info/LICENSE
bison-0.1.2.dist-info/METADATA
bison-0.1.2.dist-info/WHEEL
bison-0.1.2.dist-info/top_level.txt
bison-0.1.2.dist-info/RECORD
